{
    "northeastern.edu"      : "Northeastern University",
    "bu.edu"                : "Boston University",
    "bentley.edu"           : "Bentley",
    "uri.edu"               : "University of Rhode Island",
    "redhat.com"            : "Red Hat",
    "childrens.harvard.edu" : "Boston Childrens Hospital",
    "mclean.harvard.edu"    : "McLean Hospital",
    "meei.harvard.edu"      : "Massachusetts Eye & Ear",
    "dfci.harvard.edu"      : "Dana-Farber Cancer Institute",
    "bwh.harvard.edu"       : "Brigham and Women's Hospital",
    "bidmc.harvard.edu"     : "Beth Israel Deaconess Medical Center",
    "fas.harvard.edu"       : "Harvard University",
    "cga.harvard.edu"       : "Harvard University",
    "iq.harvard.edu"        : "Harvard University",
    "hks.harvard.edu"       : "Harvard University",
    "hsph.harvard.edu"      : "Harvard University",
    "seas.harvard.edu"      : "Harvard University",
    "gse.harvard.edu"       : "Harvard University",
    "gov.harvard.edu"       : "Harvard University",
    "oeb.harvard.edu"       : "Harvard University",
    "harvard.edu"           : "Harvard University",
    "wpi.edu"               : "Worcester Polytechnic Institute",
    "mit.edu"               : "Massachusetts Institute of Technology",
    "umass.edu"             : "University of Massachusetts Amherst",
    "uml.edu"               : "University of Massachusetts Lowell",
    "codeforboston.org"     : "Code For Boston",
    "yale.edu"              : "Yale University",
    "mmsh"                  : "Harvard University",
    "gstuart"               : "University of Massachusetts Amherst",
    "rudolph"               : "Boston Childrens Hospital",
    "robbaron"              : "Boston University",
    "kmdalton"              : "Harvard University",
    "mzink"                 : "University of Massachusetts Amherst",
    "francesco.pontiggia"   : "Harvard University"
}
